separated/__init__.py
separated/admin.py
separated/models.py
separated/tests.py
separated/utils.py
separated/views.py
django_separated-1.1.0.dist-info/top_level.txt
django_separated-1.1.0.dist-info/METADATA
django_separated-1.1.0.dist-info/DESCRIPTION.rst
django_separated-1.1.0.dist-info/metadata.json
django_separated-1.1.0.dist-info/WHEEL
django_separated-1.1.0.dist-info/RECORD
