Metadata-Version: 2.0
Name: django-separated
Version: 1.1.0
Summary: Class-based view and mixins for handling CSV with Django.
Home-page: https://github.com/fusionbox/django-separated
Author: Fusionbox, Inc.
Author-email: programmers@fusionbox.com
License: UNKNOWN
Keywords: django csv class-based views
Platform: UNKNOWN
Classifier: Development Status :: 4 - Beta
Classifier: Framework :: Django
Classifier: Intended Audience :: Developers
Classifier: License :: OSI Approved :: BSD License
Classifier: Topic :: Internet :: WWW/HTTP
Classifier: Programming Language :: Python
Classifier: Programming Language :: Python :: 2.6
Classifier: Programming Language :: Python :: 2.7
Classifier: Programming Language :: Python :: 3.2
Classifier: Programming Language :: Python :: 3.3
Requires-Dist: Django (>=1.3)
Requires-Dist: unicodecsv
